[
  {
    "ContainingType": "TASK_poiner.Controllers.EmployeeController",
    "Method": "GetAll",
    "RelativePath": "api/Employee",
    "HttpMethod": "GET",
    "IsController": true,
    "Order": 0,
    "Parameters": [],
    "ReturnTypes": []
  },
  {
    "ContainingType": "TASK_poiner.Controllers.EmployeeController",
    "Method": "Create",
    "RelativePath": "api/Employee",
    "HttpMethod": "POST",
    "IsController": true,
    "Order": 0,
    "Parameters": [
      {
        "Name": "employeeVm",
        "Type": "TASK_poiner.DTOS.EmployeeDTO",
        "IsRequired": true
      }
    ],
    "ReturnTypes": []
  },
  {
    "ContainingType": "TASK_poiner.Controllers.EmployeeController",
    "Method": "GetById",
    "RelativePath": "api/Employee/{id}",
    "HttpMethod": "GET",
    "IsController": true,
    "Order": 0,
    "Parameters": [
      {
        "Name": "id",
        "Type": "System.Int32",
        "IsRequired": true
      }
    ],
    "ReturnTypes": []
  },
  {
    "ContainingType": "TASK_poiner.Controllers.EmployeeController",
    "Method": "Update",
    "RelativePath": "api/Employee/{id}",
    "HttpMethod": "PUT",
    "IsController": true,
    "Order": 0,
    "Parameters": [
      {
        "Name": "id",
        "Type": "System.Int32",
        "IsRequired": true
      },
      {
        "Name": "employeeVm",
        "Type": "TASK_poiner.DTOS.EmployeeDTO",
        "IsRequired": true
      }
    ],
    "ReturnTypes": []
  },
  {
    "ContainingType": "TASK_poiner.Controllers.EmployeeController",
    "Method": "Delete",
    "RelativePath": "api/Employee/{id}",
    "HttpMethod": "DELETE",
    "IsController": true,
    "Order": 0,
    "Parameters": [
      {
        "Name": "id",
        "Type": "System.Int32",
        "IsRequired": true
      }
    ],
    "ReturnTypes": []
  },
  {
    "ContainingType": "TASK_poiner.Controllers.ProperyController",
    "Method": "GetAll",
    "RelativePath": "api/Propery",
    "HttpMethod": "GET",
    "IsController": true,
    "Order": 0,
    "Parameters": [],
    "ReturnTypes": []
  },
  {
    "ContainingType": "TASK_poiner.Controllers.ProperyController",
    "Method": "Add",
    "RelativePath": "api/Propery",
    "HttpMethod": "POST",
    "IsController": true,
    "Order": 0,
    "Parameters": [
      {
        "Name": "newProperty",
        "Type": "TASK_poiner.models.PropertyForEmployee",
        "IsRequired": true
      }
    ],
    "ReturnTypes": []
  },
  {
    "ContainingType": "TASK_poiner.Controllers.ProperyController",
    "Method": "GetById",
    "RelativePath": "api/Propery/{id}",
    "HttpMethod": "GET",
    "IsController": true,
    "Order": 0,
    "Parameters": [
      {
        "Name": "id",
        "Type": "System.Int32",
        "IsRequired": true
      }
    ],
    "ReturnTypes": []
  },
  {
    "ContainingType": "TASK_poiner.Controllers.ProperyController",
    "Method": "Update",
    "RelativePath": "api/Propery/{id}",
    "HttpMethod": "PUT",
    "IsController": true,
    "Order": 0,
    "Parameters": [
      {
        "Name": "updatedProperty",
        "Type": "TASK_poiner.models.PropertyForEmployee",
        "IsRequired": true
      },
      {
        "Name": "id",
        "Type": "",
        "IsRequired": true
      }
    ],
    "ReturnTypes": []
  },
  {
    "ContainingType": "TASK_poiner.Controllers.ProperyController",
    "Method": "Delete",
    "RelativePath": "api/Propery/{id}",
    "HttpMethod": "DELETE",
    "IsController": true,
    "Order": 0,
    "Parameters": [
      {
        "Name": "id",
        "Type": "System.Int32",
        "IsRequired": true
      }
    ],
    "ReturnTypes": []
  }
]